reportseff/__init__.py
reportseff/console.py
reportseff/db_inquirer.py
reportseff/job.py
reportseff/job_collection.py
reportseff/output_renderer.py
reportseff/parameters.py
reportseff-2.10.0.dist-info/LICENSE
reportseff-2.10.0.dist-info/WHEEL
reportseff-2.10.0.dist-info/entry_points.txt
reportseff-2.10.0.dist-info/METADATA
reportseff-2.10.0.dist-info/RECORD
