Metadata-Version: 2.1
Name: reportseff
Version: 2.10.0
Summary: Tablular seff output
Home-page: https://github.com/troycomi/reportseff
License: MIT
Keywords: slurm,seff
Author: Troy Comi
Author-email: troycomi@gmail.com
Requires-Python: >=3.9.1,<4.0
Classifier: License :: OSI Approved :: MIT License
Classifier: Programming Language :: Python :: 3
Classifier: Programming Language :: Python :: 3.10
Classifier: Programming Language :: Python :: 3.11
Requires-Dist: click (>=6.7)
Requires-Dist: importlib-metadata (>=4.8.2,<5.0.0) ; python_version < "3.8"
Project-URL: Repository, https://github.com/troycomi/reportseff
